{"is_source_file": false, "format": "", "description": "", "external_files": [], "external_methods": [], "published": [], "classes": [], "methods": [], "calls": [], "search-terms": [], "state": 2, "file_id": 10, "knowledge_revision": 26, "git_revision": "7dfdcc33fbce7b9e6e2fc6fc1fe5db32e602be6d", "hash": "9cb5353f74156e2c76c2cc056c9f9dc4", "format-version": 4, "code-base-name": "react_frontend", "filename": "react_frontend/package.json", "revision_history": [{"26": "7dfdcc33fbce7b9e6e2fc6fc1fe5db32e602be6d"}]}